xia_connector_ssh/__init__.py
xia_connector_ssh/connector.cpython-39-x86_64-linux-gnu.so
xia_connector_ssh-0.1.0.dist-info/LICENSE.txt
xia_connector_ssh-0.1.0.dist-info/METADATA
xia_connector_ssh-0.1.0.dist-info/WHEEL
xia_connector_ssh-0.1.0.dist-info/top_level.txt
xia_connector_ssh-0.1.0.dist-info/RECORD
