Metadata-Version: 2.1
Name: xia-connector-ssh
Version: 0.1.0
Summary: X-I-A SSH Connectors
Home-page: https://develop.x-i-a.com/docs/xia-connector-ssh/0.1.0/index.html
Author: X-I-A
Author-email: admin@x-i-a.com
License: UNKNOWN
Platform: UNKNOWN
Requires-Python: >=3.7
License-File: LICENSE.txt
Requires-Dist: paramiko
Requires-Dist: xia-engine
Requires-Dist: xia-engine-firestore
Requires-Dist: xia-meta-secret
